burny_common/__init__.py
burny_common/behavior_tree.py
burny_common/copy_file_to_server.py
burny_common/copy_folder_to_server.py
burny_common/measure_time.py
burny_common/min_heap.py
burny_common/path_manipulation.py
burny_common/run_command_on_server.py
burny_common-0.0.15.dist-info/METADATA
burny_common-0.0.15.dist-info/WHEEL
burny_common-0.0.15.dist-info/top_level.txt
burny_common-0.0.15.dist-info/RECORD
