Metadata-Version: 2.4
Name: burny_common
Version: 0.0.15
Requires-Python: <3.14,>=3.9
Requires-Dist: click>=8.1.7
Requires-Dist: loguru>=0.7.3
Requires-Dist: paramiko>=3.5.0
